Metadata-Version: 1.0
Name: identify-logline
Version: 0.0.1
Summary: identify_logline - Just a simple webhook test app
Home-page: https://github.com/jondkelley/identify_logline
Author: Jonathan Kelley
Author-email: jonkelley@gmail.com
License: Copyleft
Platform: UNKNOWN
